narrativegraphs/__init__.py
narrativegraphs/_version.py
narrativegraphs/errors.py
narrativegraphs/narrativegraph.py
narrativegraphs/db/__init__.py
narrativegraphs/db/common.py
narrativegraphs/db/cooccurrences.py
narrativegraphs/db/documents.py
narrativegraphs/db/engine.py
narrativegraphs/db/entities.py
narrativegraphs/db/predicates.py
narrativegraphs/db/relations.py
narrativegraphs/db/triplets.py
narrativegraphs/db/tuplets.py
narrativegraphs/dto/__init__.py
narrativegraphs/dto/common.py
narrativegraphs/dto/cooccurrences.py
narrativegraphs/dto/documents.py
narrativegraphs/dto/entities.py
narrativegraphs/dto/filter.py
narrativegraphs/dto/graph.py
narrativegraphs/dto/predicates.py
narrativegraphs/dto/relations.py
narrativegraphs/dto/triplets.py
narrativegraphs/nlp/__init__.py
narrativegraphs/nlp/pipeline.py
narrativegraphs/nlp/extraction/__init__.py
narrativegraphs/nlp/extraction/common.py
narrativegraphs/nlp/extraction/cooccurrences.py
narrativegraphs/nlp/extraction/spacy/__init__.py
narrativegraphs/nlp/extraction/spacy/common.py
narrativegraphs/nlp/extraction/spacy/dependencygraph.py
narrativegraphs/nlp/extraction/spacy/naive.py
narrativegraphs/nlp/filtering/__init__.py
narrativegraphs/nlp/filtering/ngrams.py
narrativegraphs/nlp/mapping/__init__.py
narrativegraphs/nlp/mapping/clustering.py
narrativegraphs/nlp/mapping/common.py
narrativegraphs/nlp/mapping/linguistic.py
narrativegraphs/nlp/utils/__init__.py
narrativegraphs/nlp/utils/spacysegmentation.py
narrativegraphs/server/__init__.py
narrativegraphs/server/app.py
narrativegraphs/server/backgroundserver.py
narrativegraphs/server/requests.py
narrativegraphs/server/routes/__init__.py
narrativegraphs/server/routes/common.py
narrativegraphs/server/routes/cooccurrences.py
narrativegraphs/server/routes/documents.py
narrativegraphs/server/routes/entities.py
narrativegraphs/server/routes/graph.py
narrativegraphs/server/routes/predicates.py
narrativegraphs/server/routes/relations.py
narrativegraphs-0.1.5.dist-info/licenses/LICENSE
narrativegraphs-0.1.5.dist-info/METADATA
narrativegraphs-0.1.5.dist-info/WHEEL
narrativegraphs-0.1.5.dist-info/top_level.txt
narrativegraphs-0.1.5.dist-info/RECORD
